ThePracticeOfReproducibleResearch/README.md
ThePracticeOfReproducibleResearch/__init__.py
ThePracticeOfReproducibleResearch/__main__.py
ThePracticeOfReproducibleResearch/file.epub
ThePracticeOfReproducibleResearch/index.html
ThePracticeOfReproducibleResearch/css/__init__.py
ThePracticeOfReproducibleResearch/css/annotations.css
ThePracticeOfReproducibleResearch/css/main.css
ThePracticeOfReproducibleResearch/css/normalize.css
ThePracticeOfReproducibleResearch/css/popup.css
ThePracticeOfReproducibleResearch/font/__init__.py
ThePracticeOfReproducibleResearch/font/fontello.eot
ThePracticeOfReproducibleResearch/font/fontello.svg
ThePracticeOfReproducibleResearch/font/fontello.ttf
ThePracticeOfReproducibleResearch/font/fontello.woff
ThePracticeOfReproducibleResearch/img/__init__.py
ThePracticeOfReproducibleResearch/img/annotator-glyph-sprite.png
ThePracticeOfReproducibleResearch/img/annotator-icon-sprite.png
ThePracticeOfReproducibleResearch/img/apple-touch-icon.png
ThePracticeOfReproducibleResearch/img/cancelfullscreen.png
ThePracticeOfReproducibleResearch/img/close.png
ThePracticeOfReproducibleResearch/img/fullscreen.png
ThePracticeOfReproducibleResearch/img/loader.gif
ThePracticeOfReproducibleResearch/img/menu-icon.png
ThePracticeOfReproducibleResearch/img/save.png
ThePracticeOfReproducibleResearch/img/saved.png
ThePracticeOfReproducibleResearch/img/settings-s.png
ThePracticeOfReproducibleResearch/img/settings.png
ThePracticeOfReproducibleResearch/img/star.png
ThePracticeOfReproducibleResearch/js/__init__.py
ThePracticeOfReproducibleResearch/js/epub.js
ThePracticeOfReproducibleResearch/js/epub.min.js
ThePracticeOfReproducibleResearch/js/epub.min.map
ThePracticeOfReproducibleResearch/js/hooks.min.js
ThePracticeOfReproducibleResearch/js/hooks.min.map
ThePracticeOfReproducibleResearch/js/reader.js
ThePracticeOfReproducibleResearch/js/reader.js.map
ThePracticeOfReproducibleResearch/js/reader.min.js
ThePracticeOfReproducibleResearch/js/reader.min.map
the_practice_of_reproducible_research-2024.3.3.0.dist-info/METADATA
the_practice_of_reproducible_research-2024.3.3.0.dist-info/WHEEL
the_practice_of_reproducible_research-2024.3.3.0.dist-info/entry_points.txt
the_practice_of_reproducible_research-2024.3.3.0.dist-info/top_level.txt
the_practice_of_reproducible_research-2024.3.3.0.dist-info/RECORD
